voc_sensor_plugin/VOC_sensor.py
voc_sensor_plugin/__init__.py
voc_sensor_plugin/additional_config.ini
voc_sensor_plugin/ui/contrib/jobs/read_voc_sensor.yaml
voc_sensor_plugin-0.1.3.dist-info/METADATA
voc_sensor_plugin-0.1.3.dist-info/WHEEL
voc_sensor_plugin-0.1.3.dist-info/entry_points.txt
voc_sensor_plugin-0.1.3.dist-info/top_level.txt
voc_sensor_plugin-0.1.3.dist-info/RECORD
